[
	{"organizationId":1,"organizationName":"National Science Foundation"},
	{"organizationId":3,"organizationName":"21th Century"},
	{"organizationId":5,"organizationName":"SUN Microsystems"},
	{"organizationId":6,"organizationName":"Pervasive Technology Labs"},
	{"organizationId":7,"organizationName":"SBC (formerly Ameritech)"},
	{"organizationId":8,"organizationName":"Center for Innovative Learning Technologies (CILT)"},
	{"organizationId":9,"organizationName":"National Academy of Sciences"},
	{"organizationId":10,"organizationName":"National Institutes of Health"},
	{"organizationId":11,"organizationName":"Indiana University's High Performance Network Applications Program"},
	{"organizationId":12,"organizationName":"German Academic Exchange Center (DAAD)"},
	{"organizationId":13,"organizationName":"Institute of Public Health NRW"},
	{"organizationId":14,"organizationName":"Forschungs- und Innovationsfond"},
	{"organizationId":15,"organizationName":"Japan International Science and Technology Exchange Center (JISTEC)"},
	{"organizationId":16,"organizationName":"Deutsche Studienstiftung"},
	{"organizationId":4,"organizationName":"UITS, Indiana University"},
	{"organizationId":20,"organizationName":"Indiana University"},
	{"organizationId":2,"organizationName":"James S. McDonnell Foundation"},
	{"organizationId":21,"organizationName":"Royal Netherlands Academy of Arts and Sciences (KNAW)"},
	{"organizationId":22,"organizationName":"Intergovernmental Personnel Act Agreement"},
	{"organizationId":23,"organizationName":"The Bill and Melinda Gates Foundation"},
	{"organizationId":24,"organizationName":"National Science Foundation Contract"},
	{"organizationId":25,"organizationName":"United States Department of Agriculture"},
	{"organizationId":26,"organizationName":"Google Inc."},
	{"organizationId":27,"organizationName":"BBSRC"},
	{"organizationId":28,"organizationName":" Indiana Economic Development Corporation"},
	{"organizationId":29,"organizationName":"National Endowment for the Humanities"},
	{"organizationId":30,"organizationName":"NET ESOLUTIONS CORPORATION (NETE) "},
	{"organizationId":31,"organizationName":"Tides Foundation"}
]
