[
	{"presentationEventId":251,"presenters":"Katy B&#246;rner###katy_borner.html"},
	{"presentationEventId":106,"presenters":"Peter A Hook###http://ella.slis.indiana.edu/~pahook/"},
	{"presentationEventId":120,"presenters":"Weixia (Bonnie) Huang###"},
	{"presentationEventId":285,"presenters":"Katy B&#246;rner###katy_borner.html"},
	{"presentationEventId":681,"presenters":"Katy B&#246;rner###katy_borner.html"},
	{"presentationEventId":264,"presenters":"Katy B&#246;rner###katy_borner.html"},
	{"presentationEventId":601,"presenters":"Michael Ginda###michael_ginda.html@@@Katy B&#246;rner###katy_borner.html"},
	{"presentationEventId":664,"presenters":"Katy B&#246;rner###katy_borner.html"},
	{"presentationEventId":647,"presenters":"Bruce W. Herr II###bruce-herr.html"},
	{"presentationEventId":497,"presenters":"Christopher Brooks###@@@Serdar Abaci###@@@Joshua Quick###@@@Katy B&#246;rner###katy_borner.html@@@George Siemens###@@@Pete Smith###"},
	{"presentationEventId":452,"presenters":"Katy B&#246;rner###katy_borner.html"},
	{"presentationEventId":496,"presenters":"Katy B&#246;rner###katy_borner.html"},
	{"presentationEventId":455,"presenters":"Katy B&#246;rner###katy_borner.html"},
	{"presentationEventId":209,"presenters":"Katy B&#246;rner###katy_borner.html"},
	{"presentationEventId":276,"presenters":"Katy B&#246;rner###katy_borner.html@@@Robert H. McDonald###@@@Ying Ding###@@@William Barnett###"},
	{"presentationEventId":665,"presenters":"Katy B&#246;rner###katy_borner.html"},
	{"presentationEventId":606,"presenters":"Katy B&#246;rner###katy_borner.html"},
	{"presentationEventId":756,"presenters":"Katy B&#246;rner###katy_borner.html"},
	{"presentationEventId":151,"presenters":"Katy B&#246;rner###katy_borner.html"},
	{"presentationEventId":253,"presenters":"Katy B&#246;rner###katy_borner.html@@@Angela Zoss###"},
	{"presentationEventId":700,"presenters":"Katy B&#246;rner###katy_borner.html@@@John Hickey###@@@Jonathan Silverstein###@@@Nils Gehlenborg###"},
	{"presentationEventId":119,"presenters":"W. Bradford Paley###"},
	{"presentationEventId":437,"presenters":"Katy B&#246;rner###katy_borner.html"},
	{"presentationEventId":518,"presenters":"Katy B&#246;rner###katy_borner.html"},
	{"presentationEventId":268,"presenters":"Katy B&#246;rner###katy_borner.html"},
	{"presentationEventId":214,"presenters":"Katy B&#246;rner###katy_borner.html"},
	{"presentationEventId":310,"presenters":"Katy B&#246;rner###katy_borner.html"},
	{"presentationEventId":397,"presenters":"Katy B&#246;rner###katy_borner.html"},
	{"presentationEventId":101,"presenters":"Katy B&#246;rner###katy_borner.html"},
	{"presentationEventId":20,"presenters":"Katy B&#246;rner###katy_borner.html"},
	{"presentationEventId":339,"presenters":"Katy B&#246;rner###katy_borner.html"},
	{"presentationEventId":330,"presenters":"Katy B&#246;rner###katy_borner.html"},
	{"presentationEventId":25,"presenters":"Katy B&#246;rner###katy_borner.html@@@Shashikant Penumarthy###"},
	{"presentationEventId":359,"presenters":"Chin Hua Kong###"},
	{"presentationEventId":26,"presenters":"Katy B&#246;rner###katy_borner.html"},
	{"presentationEventId":213,"presenters":"Katy B&#246;rner###katy_borner.html"},
	{"presentationEventId":137,"presenters":"Katy B&#246;rner###katy_borner.html"},
	{"presentationEventId":745,"presenters":"Supriya Bidanta###supriya_bidanta.html@@@Katy B&#246;rner###katy_borner.html@@@Yashvardhan Jain###yashvardhan-jain.html"},
	{"presentationEventId":265,"presenters":"Katy B&#246;rner###katy_borner.html"},
	{"presentationEventId":379,"presenters":"Katy B&#246;rner###katy_borner.html"},
	{"presentationEventId":405,"presenters":"Katy B&#246;rner###katy_borner.html"},
	{"presentationEventId":292,"presenters":"Katy B&#246;rner###katy_borner.html"},
	{"presentationEventId":136,"presenters":"Peter A Hook###http://ella.slis.indiana.edu/~pahook/"},
	{"presentationEventId":196,"presenters":"Nianli Ma###@@@Russell Jackson Duhon###"},
	{"presentationEventId":218,"presenters":"Katy B&#246;rner###katy_borner.html"},
	{"presentationEventId":373,"presenters":"David E. Polley###"},
	{"presentationEventId":238,"presenters":"Katy B&#246;rner###katy_borner.html@@@Javed Mostafa###"},
	{"presentationEventId":27,"presenters":"Katy B&#246;rner###katy_borner.html"},
	{"presentationEventId":230,"presenters":"Katy B&#246;rner###katy_borner.html"},
	{"presentationEventId":414,"presenters":"Katy B&#246;rner###katy_borner.html@@@Ann Beynon###"},
	{"presentationEventId":449,"presenters":"Katy B&#246;rner###katy_borner.html"},
	{"presentationEventId":667,"presenters":"Katy B&#246;rner###katy_borner.html"},
	{"presentationEventId":149,"presenters":"Weixia (Bonnie) Huang###@@@Bruce W. Herr II###bruce-herr.html@@@Katy B&#246;rner###katy_borner.html@@@Ben Markines###"},
	{"presentationEventId":93,"presenters":"Soma Sanyal###"},
	{"presentationEventId":733,"presenters":"Katy B&#246;rner###katy_borner.html"},
	{"presentationEventId":307,"presenters":"Scott B. Weingart###http://www.scottbot.net/"},
	{"presentationEventId":382,"presenters":"Katy B&#246;rner###katy_borner.html"},
	{"presentationEventId":335,"presenters":"Katy B&#246;rner###katy_borner.html"},
	{"presentationEventId":706,"presenters":"Katy B&#246;rner###katy_borner.html@@@Andreas Bueckle###andreas_bueckle.html@@@Bruce W. Herr II###bruce-herr.html@@@Libby  Maier###libby-maier.html"},
	{"presentationEventId":191,"presenters":"Katy B&#246;rner###katy_borner.html"},
	{"presentationEventId":295,"presenters":"Katy B&#246;rner###katy_borner.html"},
	{"presentationEventId":714,"presenters":"Katy B&#246;rner###katy_borner.html"},
	{"presentationEventId":11,"presenters":"Peter A Hook###http://ella.slis.indiana.edu/~pahook/"},
	{"presentationEventId":135,"presenters":"Peter A Hook###http://ella.slis.indiana.edu/~pahook/"},
	{"presentationEventId":228,"presenters":"Andrea Scharnhorst###@@@Katy B&#246;rner###katy_borner.html"},
	{"presentationEventId":252,"presenters":"Katy B&#246;rner###katy_borner.html"},
	{"presentationEventId":523,"presenters":"CNS, IUNI, UITS ###"},
	{"presentationEventId":39,"presenters":"Katy B&#246;rner###katy_borner.html"},
	{"presentationEventId":537,"presenters":"Katy B&#246;rner###katy_borner.html"},
	{"presentationEventId":508,"presenters":"Katy B&#246;rner###katy_borner.html"},
	{"presentationEventId":526,"presenters":"Katy B&#246;rner###katy_borner.html"},
	{"presentationEventId":489,"presenters":"Katy B&#246;rner###katy_borner.html"},
	{"presentationEventId":559,"presenters":"Katy B&#246;rner###katy_borner.html"},
	{"presentationEventId":131,"presenters":"Katy B&#246;rner###katy_borner.html"},
	{"presentationEventId":662,"presenters":"Katy B&#246;rner###katy_borner.html@@@MC-IU, IEC, TMCs and others ###"},
	{"presentationEventId":178,"presenters":"Katy B&#246;rner###katy_borner.html"},
	{"presentationEventId":255,"presenters":"Katy B&#246;rner###katy_borner.html"},
	{"presentationEventId":241,"presenters":"Katy B&#246;rner###katy_borner.html"},
	{"presentationEventId":357,"presenters":"Katy B&#246;rner###katy_borner.html"},
	{"presentationEventId":465,"presenters":"Ashish Shendure###@@@Katy B&#246;rner###katy_borner.html"},
	{"presentationEventId":17,"presenters":"Katy B&#246;rner###katy_borner.html@@@Ketan K. Mane###"},
	{"presentationEventId":325,"presenters":"Katy B&#246;rner###katy_borner.html"},
	{"presentationEventId":66,"presenters":"Katy B&#246;rner###katy_borner.html"},
	{"presentationEventId":142,"presenters":"Katy B&#246;rner###katy_borner.html"},
	{"presentationEventId":479,"presenters":"Katy B&#246;rner###katy_borner.html"},
	{"presentationEventId":160,"presenters":"Katy B&#246;rner###katy_borner.html@@@Javed Mostafa###"},
	{"presentationEventId":640,"presenters":"Olga Scrivner###olga-scrivner.html@@@William Trochim###@@@Katy B&#246;rner###katy_borner.html"},
	{"presentationEventId":284,"presenters":"Katy B&#246;rner###katy_borner.html"},
	{"presentationEventId":33,"presenters":"Katy B&#246;rner###katy_borner.html@@@Deborah MacPherson###"},
	{"presentationEventId":512,"presenters":"Katy B&#246;rner###katy_borner.html@@@Robert Goldstone###http://cognitrn.psych.indiana.edu/rgoldsto/rob.html@@@Franco Pestilli###"},
	{"presentationEventId":633,"presenters":"Katy B&#246;rner###katy_borner.html"},
	{"presentationEventId":442,"presenters":"Katy B&#246;rner###katy_borner.html"},
	{"presentationEventId":57,"presenters":"Katy B&#246;rner###katy_borner.html"},
	{"presentationEventId":109,"presenters":"Katy B&#246;rner###katy_borner.html"},
	{"presentationEventId":239,"presenters":"Katy B&#246;rner###katy_borner.html"},
	{"presentationEventId":31,"presenters":"Peter A Hook###http://ella.slis.indiana.edu/~pahook/"},
	{"presentationEventId":288,"presenters":"Angela Zoss###"},
	{"presentationEventId":524,"presenters":"Katy B&#246;rner###katy_borner.html"},
	{"presentationEventId":34,"presenters":"Katy B&#246;rner###katy_borner.html"},
	{"presentationEventId":505,"presenters":"Andreas Bueckle###andreas_bueckle.html"},
	{"presentationEventId":12,"presenters":"Peter A Hook###http://ella.slis.indiana.edu/~pahook/"},
	{"presentationEventId":296,"presenters":"Katy B&#246;rner###katy_borner.html"},
	{"presentationEventId":686,"presenters":"Jyl Boline###@@@Bruce W. Herr II###bruce-herr.html"},
	{"presentationEventId":282,"presenters":"Katy B&#246;rner###katy_borner.html"},
	{"presentationEventId":10,"presenters":"Peter A Hook###http://ella.slis.indiana.edu/~pahook/"},
	{"presentationEventId":321,"presenters":"Katy B&#246;rner###katy_borner.html"},
	{"presentationEventId":428,"presenters":"Katy B&#246;rner###katy_borner.html"},
	{"presentationEventId":324,"presenters":"Katy B&#246;rner###katy_borner.html"},
	{"presentationEventId":684,"presenters":"Katy B&#246;rner###katy_borner.html"},
	{"presentationEventId":18,"presenters":"Ketan K. Mane###@@@Sidharth Thakur###@@@YueYu Fu###"},
	{"presentationEventId":139,"presenters":"Katy B&#246;rner###katy_borner.html"},
	{"presentationEventId":146,"presenters":"Weixia (Bonnie) Huang###"},
	{"presentationEventId":614,"presenters":"Katy B&#246;rner###katy_borner.html@@@Mike Hu###"},
	{"presentationEventId":752,"presenters":"Katy B&#246;rner###katy_borner.html@@@Lisel Record###lisel_record.html@@@Todd Theriault###todd_theriault.html@@@David Chavalarias###@@@Andreas  Scharnhorst###@@@Nicolas Gutehrle###@@@Iana Atanassova###@@@Yunwei Chen###@@@Sarah  Huggett###"},
	{"presentationEventId":143,"presenters":"Katy B&#246;rner###katy_borner.html"},
	{"presentationEventId":98,"presenters":"Katy B&#246;rner###katy_borner.html"},
	{"presentationEventId":424,"presenters":"Katy B&#246;rner###katy_borner.html"},
	{"presentationEventId":594,"presenters":"Katy B&#246;rner###katy_borner.html"},
	{"presentationEventId":193,"presenters":"Katy B&#246;rner###katy_borner.html"},
	{"presentationEventId":381,"presenters":"David E. Polley###"},
	{"presentationEventId":408,"presenters":"Robert Light###"},
	{"presentationEventId":655,"presenters":"Anna Keune###@@@Kylie Peppler###"},
	{"presentationEventId":466,"presenters":"Robert Light###@@@Daniel O'Donnell###"},
	{"presentationEventId":243,"presenters":"Katy B&#246;rner###katy_borner.html@@@Yuezheng Zhou###"},
	{"presentationEventId":617,"presenters":"Katy B&#246;rner###katy_borner.html"},
	{"presentationEventId":674,"presenters":"Katy B&#246;rner###katy_borner.html"},
	{"presentationEventId":167,"presenters":"Peter A Hook###http://ella.slis.indiana.edu/~pahook/"},
	{"presentationEventId":250,"presenters":"Katy B&#246;rner###katy_borner.html"},
	{"presentationEventId":672,"presenters":"Leah Scherschel###leah_scherschel.html"},
	{"presentationEventId":64,"presenters":"Katy B&#246;rner###katy_borner.html"},
	{"presentationEventId":145,"presenters":"Weixia (Bonnie) Huang###@@@Katy B&#246;rner###katy_borner.html@@@Russell Jackson Duhon###@@@Bruce W. Herr II###bruce-herr.html@@@Timothy Kelley###@@@Santiago Schnell###"},
	{"presentationEventId":582,"presenters":"Olga Scrivner###olga-scrivner.html"},
	{"presentationEventId":458,"presenters":"Katy B&#246;rner###katy_borner.html@@@Robert Light###"},
	{"presentationEventId":198,"presenters":"Katy B&#246;rner###katy_borner.html"},
	{"presentationEventId":104,"presenters":"Katy B&#246;rner###katy_borner.html"},
	{"presentationEventId":163,"presenters":"Katy B&#246;rner###katy_borner.html"},
	{"presentationEventId":413,"presenters":"Katy B&#246;rner###katy_borner.html"},
	{"presentationEventId":102,"presenters":"Katy B&#246;rner###katy_borner.html"},
	{"presentationEventId":315,"presenters":"Katy B&#246;rner###katy_borner.html"},
	{"presentationEventId":71,"presenters":"Katy B&#246;rner###katy_borner.html"},
	{"presentationEventId":588,"presenters":"Katy B&#246;rner###katy_borner.html"},
	{"presentationEventId":2,"presenters":"Katy B&#246;rner###katy_borner.html"},
	{"presentationEventId":72,"presenters":"Katy B&#246;rner###katy_borner.html"},
	{"presentationEventId":343,"presenters":"Joseph R. Biberstine###"},
	{"presentationEventId":234,"presenters":"Katy B&#246;rner###katy_borner.html"},
	{"presentationEventId":177,"presenters":"Katy B&#246;rner###katy_borner.html"},
	{"presentationEventId":626,"presenters":"Katy B&#246;rner###katy_borner.html"},
	{"presentationEventId":346,"presenters":"Katy B&#246;rner###katy_borner.html"},
	{"presentationEventId":705,"presenters":"Andreas Bueckle###andreas_bueckle.html@@@Ellen M. Quardokus###"},
	{"presentationEventId":480,"presenters":"Griffin Weber###@@@Daniel O'Donnell###"},
	{"presentationEventId":337,"presenters":"Katy B&#246;rner###katy_borner.html"},
	{"presentationEventId":280,"presenters":"Katy B&#246;rner###katy_borner.html"},
	{"presentationEventId":727,"presenters":"Andreas Bueckle###andreas_bueckle.html@@@Katy B&#246;rner###katy_borner.html"},
	{"presentationEventId":696,"presenters":"Kristen Browne###@@@Heidi Schlehlein###schlehlein-heidi.html@@@Rachel Bajema###rachel-bajema.html"},
	{"presentationEventId":297,"presenters":"Katy B&#246;rner###katy_borner.html"},
	{"presentationEventId":459,"presenters":"Katy B&#246;rner###katy_borner.html"},
	{"presentationEventId":314,"presenters":"Katy B&#246;rner###katy_borner.html"},
	{"presentationEventId":391,"presenters":"Colin Allen###@@@Katy B&#246;rner###katy_borner.html@@@Andrew Ravenscroft###@@@David Bourget###@@@Chris Reed###"},
	{"presentationEventId":444,"presenters":"Mary Ann Wojton###@@@Lisel Record###lisel_record.html@@@Sasha Palmquist###"},
	{"presentationEventId":274,"presenters":"Scott B. Weingart###http://www.scottbot.net/@@@Katy B&#246;rner###katy_borner.html"},
	{"presentationEventId":400,"presenters":"Katy B&#246;rner###katy_borner.html"},
	{"presentationEventId":689,"presenters":"Jared Nedzel###@@@Katy B&#246;rner###katy_borner.html@@@Bruce W. Herr II###bruce-herr.html@@@Andreas Bueckle###andreas_bueckle.html@@@Kristin Ardlie###"},
	{"presentationEventId":320,"presenters":"Katy B&#246;rner###katy_borner.html@@@Joseph R. Biberstine###"},
	{"presentationEventId":426,"presenters":"Katy B&#246;rner###katy_borner.html"},
	{"presentationEventId":595,"presenters":"Katy B&#246;rner###katy_borner.html"},
	{"presentationEventId":47,"presenters":"Katy B&#246;rner###katy_borner.html"},
	{"presentationEventId":412,"presenters":"Katy B&#246;rner###katy_borner.html"},
	{"presentationEventId":651,"presenters":"Katy B&#246;rner###katy_borner.html"},
	{"presentationEventId":741,"presenters":"Katy B&#246;rner###katy_borner.html@@@Sam  Learner###@@@Beatriz  Malveiro ###@@@Rita  Costa ###@@@Elizabeth Record###@@@Liuhuaying  Yang###"},
	{"presentationEventId":211,"presenters":"Katy B&#246;rner###katy_borner.html"},
	{"presentationEventId":46,"presenters":"Katy B&#246;rner###katy_borner.html"},
	{"presentationEventId":83,"presenters":"Peter A Hook###http://ella.slis.indiana.edu/~pahook/"},
	{"presentationEventId":15,"presenters":"Stacy Kowalczyk###"},
	{"presentationEventId":304,"presenters":"Katy B&#246;rner###katy_borner.html"},
	{"presentationEventId":361,"presenters":"Andr&#233; Skupin###http://geography.sdsu.edu/People/Pages/skupin/index.htm"},
	{"presentationEventId":77,"presenters":"Katy B&#246;rner###katy_borner.html"},
	{"presentationEventId":125,"presenters":"Katy B&#246;rner###katy_borner.html"},
	{"presentationEventId":140,"presenters":"Katy B&#246;rner###katy_borner.html"},
	{"presentationEventId":687,"presenters":"Katy B&#246;rner###katy_borner.html"},
	{"presentationEventId":153,"presenters":"Bruce W. Herr II###bruce-herr.html"},
	{"presentationEventId":73,"presenters":"Katy B&#246;rner###katy_borner.html"},
	{"presentationEventId":631,"presenters":"Katy B&#246;rner###katy_borner.html@@@MC-IU HIVE HuBMAP Team ###"},
	{"presentationEventId":40,"presenters":"Katy B&#246;rner###katy_borner.html"},
	{"presentationEventId":56,"presenters":"Katy B&#246;rner###katy_borner.html"},
	{"presentationEventId":355,"presenters":"Katy B&#246;rner###katy_borner.html@@@Robert H. McDonald###@@@Ying Ding###@@@William Barnett###"},
	{"presentationEventId":590,"presenters":"Katy B&#246;rner###katy_borner.html"},
	{"presentationEventId":579,"presenters":"Katy B&#246;rner###katy_borner.html"},
	{"presentationEventId":277,"presenters":"Katy B&#246;rner###katy_borner.html@@@Kevin W. Boyack###"},
	{"presentationEventId":729,"presenters":"Katy B&#246;rner###katy_borner.html@@@Jeff Spraggins###"},
	{"presentationEventId":261,"presenters":"Katy B&#246;rner###katy_borner.html"},
	{"presentationEventId":123,"presenters":"Chung-Yang (Kenneth) Lee###"},
	{"presentationEventId":348,"presenters":"Katy B&#246;rner###katy_borner.html"},
	{"presentationEventId":332,"presenters":"Katy B&#246;rner###katy_borner.html"},
	{"presentationEventId":468,"presenters":"Katy B&#246;rner###katy_borner.html"},
	{"presentationEventId":333,"presenters":"Katy B&#246;rner###katy_borner.html"},
	{"presentationEventId":575,"presenters":"Olga Scrivner###olga-scrivner.html@@@Kosali Simon###"},
	{"presentationEventId":730,"presenters":"Katy B&#246;rner###katy_borner.html@@@Michael Ginda###michael_ginda.html@@@Nancy Ruschman###nancy_ruschman.html"},
	{"presentationEventId":484,"presenters":"Katy B&#246;rner###katy_borner.html"},
	{"presentationEventId":569,"presenters":"Lisel Record###lisel_record.html"},
	{"presentationEventId":712,"presenters":"Ellen M. Quardokus###"},
	{"presentationEventId":404,"presenters":"Katy B&#246;rner###katy_borner.html"},
	{"presentationEventId":507,"presenters":"Katy B&#246;rner###katy_borner.html"},
	{"presentationEventId":596,"presenters":"Katy B&#246;rner###katy_borner.html"},
	{"presentationEventId":233,"presenters":"Katy B&#246;rner###katy_borner.html"},
	{"presentationEventId":547,"presenters":"Katy B&#246;rner###katy_borner.html"},
	{"presentationEventId":578,"presenters":"Katy B&#246;rner###katy_borner.html"},
	{"presentationEventId":556,"presenters":"Olga Scrivner###olga-scrivner.html"},
	{"presentationEventId":376,"presenters":"Katy B&#246;rner###katy_borner.html"},
	{"presentationEventId":226,"presenters":"Katy B&#246;rner###katy_borner.html"},
	{"presentationEventId":500,"presenters":"Katy B&#246;rner###katy_borner.html"},
	{"presentationEventId":13,"presenters":"Peter A Hook###http://ella.slis.indiana.edu/~pahook/"},
	{"presentationEventId":723,"presenters":"Griffin Weber###"},
	{"presentationEventId":515,"presenters":"Lisel Record###lisel_record.html"},
	{"presentationEventId":91,"presenters":"Stacy Kowalczyk###"},
	{"presentationEventId":695,"presenters":"Supriya Bidanta###supriya_bidanta.html"},
	{"presentationEventId":737,"presenters":"Rachel Bajema###rachel-bajema.html"},
	{"presentationEventId":433,"presenters":"Katy B&#246;rner###katy_borner.html"},
	{"presentationEventId":303,"presenters":"Katy B&#246;rner###katy_borner.html"},
	{"presentationEventId":540,"presenters":"Jivitesh Poojary###jivitesh-poojary.html@@@Olga Scrivner###olga-scrivner.html@@@Katy B&#246;rner###katy_borner.html"},
	{"presentationEventId":293,"presenters":"Katy B&#246;rner###katy_borner.html"},
	{"presentationEventId":365,"presenters":"Robert H. McDonald###@@@Jim Myers###@@@Katy B&#246;rner###katy_borner.html@@@Beth Plale###@@@Margaret Hedstrom###@@@Jude Yew###@@@Robert Light###@@@David Cliff###@@@Ryan Cobine###@@@Stacy Kowalczyk###@@@Kavitha Chrandasekar###@@@Zaman Aktaruzzaman###@@@Rob Kooper###@@@Luigi Marini###@@@Ann Zimmerman###@@@Ram Prasanna###@@@Praveen Kumar###@@@Terry McLaren###"},
	{"presentationEventId":610,"presenters":"Katy B&#246;rner###katy_borner.html"},
	{"presentationEventId":165,"presenters":"Katy B&#246;rner###katy_borner.html"},
	{"presentationEventId":287,"presenters":"Joseph R. Biberstine###"},
	{"presentationEventId":748,"presenters":"Heidi Schlehlein###schlehlein-heidi.html@@@Ushma Patel###ushma-patel.html@@@Rachel Bajema###rachel-bajema.html"},
	{"presentationEventId":21,"presenters":"Katy B&#246;rner###katy_borner.html"},
	{"presentationEventId":152,"presenters":"Katy B&#246;rner###katy_borner.html"},
	{"presentationEventId":475,"presenters":"Michael Ginda###michael_ginda.html"},
	{"presentationEventId":536,"presenters":"Katy B&#246;rner###katy_borner.html"},
	{"presentationEventId":719,"presenters":"Katy B&#246;rner###katy_borner.html@@@Andreas Bueckle###andreas_bueckle.html"},
	{"presentationEventId":401,"presenters":"Katy B&#246;rner###katy_borner.html"},
	{"presentationEventId":5,"presenters":"Katy B&#246;rner###katy_borner.html"},
	{"presentationEventId":281,"presenters":"Robin M. Wagner###@@@Katy B&#246;rner###katy_borner.html"},
	{"presentationEventId":462,"presenters":"Katy B&#246;rner###katy_borner.html"},
	{"presentationEventId":301,"presenters":"Angela Zoss###@@@Katy B&#246;rner###katy_borner.html"},
	{"presentationEventId":461,"presenters":"Katy B&#246;rner###katy_borner.html"},
	{"presentationEventId":499,"presenters":"Katy B&#246;rner###katy_borner.html"},
	{"presentationEventId":340,"presenters":"Katy B&#246;rner###katy_borner.html"},
	{"presentationEventId":498,"presenters":"Katy B&#246;rner###katy_borner.html@@@Xiaoran Yan###@@@Adam Ploszaj###"},
	{"presentationEventId":367,"presenters":"Katy B&#246;rner###katy_borner.html"},
	{"presentationEventId":661,"presenters":"Katy B&#246;rner###katy_borner.html"},
	{"presentationEventId":392,"presenters":"Katy B&#246;rner###katy_borner.html"},
	{"presentationEventId":298,"presenters":"Katy B&#246;rner###katy_borner.html"},
	{"presentationEventId":609,"presenters":"Katy B&#246;rner###katy_borner.html"},
	{"presentationEventId":429,"presenters":"Katy B&#246;rner###katy_borner.html"},
	{"presentationEventId":519,"presenters":"Adam Simpson###@@@Gagandeep  Singh###@@@Katy B&#246;rner###katy_borner.html"},
	{"presentationEventId":432,"presenters":"Katy B&#246;rner###katy_borner.html"},
	{"presentationEventId":690,"presenters":"Katy B&#246;rner###katy_borner.html@@@Kristin Ardlie###"},
	{"presentationEventId":112,"presenters":"Katy B&#246;rner###katy_borner.html"},
	{"presentationEventId":254,"presenters":"Katy B&#246;rner###katy_borner.html"},
	{"presentationEventId":656,"presenters":"Katy B&#246;rner###katy_borner.html@@@Philip Beesley###@@@Gabriel Lubell###"},
	{"presentationEventId":96,"presenters":"Ketan K. Mane###"},
	{"presentationEventId":694,"presenters":"Andreas Bueckle###andreas_bueckle.html"},
	{"presentationEventId":581,"presenters":"Yue Chen###@@@Kenneth Steimel###@@@Yingnan Ju###"},
	{"presentationEventId":396,"presenters":"Todd Theriault###todd_theriault.html@@@Katy B&#246;rner###katy_borner.html"},
	{"presentationEventId":107,"presenters":"Katy B&#246;rner###katy_borner.html"},
	{"presentationEventId":679,"presenters":"Katy B&#246;rner###katy_borner.html"},
	{"presentationEventId":600,"presenters":"Katy B&#246;rner###katy_borner.html"},
	{"presentationEventId":319,"presenters":"Katy B&#246;rner###katy_borner.html"},
	{"presentationEventId":221,"presenters":"Katy B&#246;rner###katy_borner.html"},
	{"presentationEventId":435,"presenters":"Katy B&#246;rner###katy_borner.html"},
	{"presentationEventId":653,"presenters":"Katy B&#246;rner###katy_borner.html"},
	{"presentationEventId":576,"presenters":"Katy B&#246;rner###katy_borner.html"},
	{"presentationEventId":759,"presenters":"Katy B&#246;rner###katy_borner.html"},
	{"presentationEventId":258,"presenters":"Katy B&#246;rner###katy_borner.html"},
	{"presentationEventId":19,"presenters":"Katy B&#246;rner###katy_borner.html"},
	{"presentationEventId":398,"presenters":"Brianna Marshall###http://www.briannamarshall.com/@@@David E. Polley###"},
	{"presentationEventId":589,"presenters":"Katy B&#246;rner###katy_borner.html"},
	{"presentationEventId":108,"presenters":"Gavin LaRowe###"},
	{"presentationEventId":215,"presenters":"Katy B&#246;rner###katy_borner.html"},
	{"presentationEventId":65,"presenters":"Kevin W. Boyack###@@@Katy B&#246;rner###katy_borner.html@@@Ketan K. Mane###"},
	{"presentationEventId":52,"presenters":"Katy B&#246;rner###katy_borner.html"},
	{"presentationEventId":317,"presenters":"Katy B&#246;rner###katy_borner.html"},
	{"presentationEventId":366,"presenters":"Katy B&#246;rner###katy_borner.html"},
	{"presentationEventId":635,"presenters":"Katy B&#246;rner###katy_borner.html"},
	{"presentationEventId":440,"presenters":"Katy B&#246;rner###katy_borner.html"},
	{"presentationEventId":37,"presenters":"Katy B&#246;rner###katy_borner.html"},
	{"presentationEventId":85,"presenters":"Katy B&#246;rner###katy_borner.html"},
	{"presentationEventId":32,"presenters":"Peter A Hook###http://ella.slis.indiana.edu/~pahook/"},
	{"presentationEventId":421,"presenters":"Katy B&#246;rner###katy_borner.html"},
	{"presentationEventId":546,"presenters":"Olga Scrivner###olga-scrivner.html@@@Nitocris Perez###@@@Julie  Madewell###@@@Cameron Buckley###"},
	{"presentationEventId":358,"presenters":"Katy B&#246;rner###katy_borner.html@@@Todd Theriault###todd_theriault.html"},
	{"presentationEventId":164,"presenters":"Katy B&#246;rner###katy_borner.html"},
	{"presentationEventId":701,"presenters":"Katy B&#246;rner###katy_borner.html"},
	{"presentationEventId":326,"presenters":"Katy B&#246;rner###katy_borner.html"},
	{"presentationEventId":704,"presenters":"Katy B&#246;rner###katy_borner.html"},
	{"presentationEventId":78,"presenters":"Katy B&#246;rner###katy_borner.html"},
	{"presentationEventId":278,"presenters":"Katy B&#246;rner###katy_borner.html"},
	{"presentationEventId":603,"presenters":"Olga Scrivner###olga-scrivner.html@@@Julie  Madewell###"},
	{"presentationEventId":133,"presenters":"Peter A Hook###http://ella.slis.indiana.edu/~pahook/"},
	{"presentationEventId":289,"presenters":"Katy B&#246;rner###katy_borner.html"},
	{"presentationEventId":637,"presenters":"Katy B&#246;rner###katy_borner.html"},
	{"presentationEventId":279,"presenters":"Katy B&#246;rner###katy_borner.html"},
	{"presentationEventId":100,"presenters":"Bruce W. Herr II###bruce-herr.html"},
	{"presentationEventId":443,"presenters":"Katy B&#246;rner###katy_borner.html"},
	{"presentationEventId":416,"presenters":"Katy B&#246;rner###katy_borner.html"},
	{"presentationEventId":492,"presenters":"Robert Light###"},
	{"presentationEventId":638,"presenters":"Katy B&#246;rner###katy_borner.html"},
	{"presentationEventId":755,"presenters":"Katy B&#246;rner###katy_borner.html"},
	{"presentationEventId":758,"presenters":"Michael Ginda###michael_ginda.html"},
	{"presentationEventId":232,"presenters":"Katy B&#246;rner###katy_borner.html"},
	{"presentationEventId":692,"presenters":"Katy B&#246;rner###katy_borner.html"},
	{"presentationEventId":427,"presenters":"Katy B&#246;rner###katy_borner.html"},
	{"presentationEventId":158,"presenters":"Katy B&#246;rner###katy_borner.html"},
	{"presentationEventId":739,"presenters":"Andreas Bueckle###andreas_bueckle.html"},
	{"presentationEventId":113,"presenters":"Katy B&#246;rner###katy_borner.html"},
	{"presentationEventId":377,"presenters":"Katy B&#246;rner###katy_borner.html"},
	{"presentationEventId":24,"presenters":"Katy B&#246;rner###katy_borner.html"},
	{"presentationEventId":170,"presenters":"Weixia (Bonnie) Huang###"},
	{"presentationEventId":403,"presenters":"Katy B&#246;rner###katy_borner.html"},
	{"presentationEventId":494,"presenters":"Katy B&#246;rner###katy_borner.html"},
	{"presentationEventId":55,"presenters":"Katy B&#246;rner###katy_borner.html"},
	{"presentationEventId":68,"presenters":"Katy B&#246;rner###katy_borner.html"},
	{"presentationEventId":374,"presenters":"Katy B&#246;rner###katy_borner.html"},
	{"presentationEventId":652,"presenters":"Katy B&#246;rner###katy_borner.html@@@James Gee###@@@Peter Hunter###"},
	{"presentationEventId":535,"presenters":"Katy B&#246;rner###katy_borner.html"},
	{"presentationEventId":244,"presenters":"Katy B&#246;rner###katy_borner.html"},
	{"presentationEventId":565,"presenters":"Katy B&#246;rner###katy_borner.html"},
	{"presentationEventId":38,"presenters":"Katy B&#246;rner###katy_borner.html"},
	{"presentationEventId":128,"presenters":"Katy B&#246;rner###katy_borner.html"},
	{"presentationEventId":456,"presenters":"Katy B&#246;rner###katy_borner.html"},
	{"presentationEventId":728,"presenters":"Heidi Schlehlein###schlehlein-heidi.html@@@Rachel Bajema###rachel-bajema.html"},
	{"presentationEventId":300,"presenters":"Katy B&#246;rner###katy_borner.html"},
	{"presentationEventId":353,"presenters":"David E. Polley###"},
	{"presentationEventId":722,"presenters":"Todd Theriault###todd_theriault.html"},
	{"presentationEventId":256,"presenters":"Katy B&#246;rner###katy_borner.html"},
	{"presentationEventId":216,"presenters":"Katy B&#246;rner###katy_borner.html"},
	{"presentationEventId":646,"presenters":"Katy B&#246;rner###katy_borner.html"},
	{"presentationEventId":202,"presenters":"Ann L McCranie###"},
	{"presentationEventId":266,"presenters":"Katy B&#246;rner###katy_borner.html"},
	{"presentationEventId":725,"presenters":"Ondine Cleaver###"},
	{"presentationEventId":129,"presenters":"Katy B&#246;rner###katy_borner.html"},
	{"presentationEventId":744,"presenters":"Katy B&#246;rner###katy_borner.html"},
	{"presentationEventId":8,"presenters":"Hardik Sheth###"},
	{"presentationEventId":707,"presenters":"Katy B&#246;rner###katy_borner.html"},
	{"presentationEventId":305,"presenters":"Katy B&#246;rner###katy_borner.html"},
	{"presentationEventId":318,"presenters":"Katy B&#246;rner###katy_borner.html"},
	{"presentationEventId":312,"presenters":"Katy B&#246;rner###katy_borner.html"},
	{"presentationEventId":683,"presenters":"Katy B&#246;rner###katy_borner.html"},
	{"presentationEventId":179,"presenters":"Russell Jackson Duhon###"},
	{"presentationEventId":470,"presenters":"Katy B&#246;rner###katy_borner.html"},
	{"presentationEventId":571,"presenters":"Katy B&#246;rner###katy_borner.html"},
	{"presentationEventId":685,"presenters":"Katy B&#246;rner###katy_borner.html@@@Kristin Ardlie###"},
	{"presentationEventId":693,"presenters":"Michael Ginda###michael_ginda.html"},
	{"presentationEventId":370,"presenters":"Katy B&#246;rner###katy_borner.html"},
	{"presentationEventId":99,"presenters":"Bruce W. Herr II###bruce-herr.html"},
	{"presentationEventId":48,"presenters":"Katy B&#246;rner###katy_borner.html"},
	{"presentationEventId":28,"presenters":"Katy B&#246;rner###katy_borner.html"},
	{"presentationEventId":732,"presenters":"Katy B&#246;rner###katy_borner.html"},
	{"presentationEventId":262,"presenters":"Katy B&#246;rner###katy_borner.html"},
	{"presentationEventId":313,"presenters":"Katy B&#246;rner###katy_borner.html"},
	{"presentationEventId":699,"presenters":"Katy B&#246;rner###katy_borner.html@@@Ellen M. Quardokus###"},
	{"presentationEventId":204,"presenters":"Katy B&#246;rner###katy_borner.html"},
	{"presentationEventId":362,"presenters":"David E. Polley###@@@Katy B&#246;rner###katy_borner.html"},
	{"presentationEventId":162,"presenters":"Katy B&#246;rner###katy_borner.html@@@Michael Boyles###@@@Elijah Wright###"},
	{"presentationEventId":30,"presenters":"Katy B&#246;rner###katy_borner.html"},
	{"presentationEventId":356,"presenters":"David E. Polley###@@@Katy B&#246;rner###katy_borner.html"},
	{"presentationEventId":299,"presenters":"Katy B&#246;rner###katy_borner.html"},
	{"presentationEventId":95,"presenters":"Ketan K. Mane###"},
	{"presentationEventId":585,"presenters":"Katy B&#246;rner###katy_borner.html"},
	{"presentationEventId":122,"presenters":"Robert Goldstone###http://cognitrn.psych.indiana.edu/rgoldsto/rob.html"},
	{"presentationEventId":62,"presenters":"Katy B&#246;rner###katy_borner.html@@@Bruce W. Herr II###bruce-herr.html"},
	{"presentationEventId":514,"presenters":"Nan Li###@@@Zheng Gao###@@@Katy B&#246;rner###katy_borner.html@@@Naren Suri###@@@Zeyuan Liu###"},
	{"presentationEventId":329,"presenters":"Katy B&#246;rner###katy_borner.html"},
	{"presentationEventId":751,"presenters":"Katy B&#246;rner###katy_borner.html"},
	{"presentationEventId":454,"presenters":"Gerhard Kilmeck###@@@Katy B&#246;rner###katy_borner.html@@@Michael Zentner###"},
	{"presentationEventId":180,"presenters":"Katy B&#246;rner###katy_borner.html"},
	{"presentationEventId":390,"presenters":"Katy B&#246;rner###katy_borner.html"},
	{"presentationEventId":127,"presenters":"Gavin LaRowe###"},
	{"presentationEventId":439,"presenters":"Katy B&#246;rner###katy_borner.html"},
	{"presentationEventId":669,"presenters":"Katy B&#246;rner###katy_borner.html"},
	{"presentationEventId":675,"presenters":"Katy B&#246;rner###katy_borner.html"},
	{"presentationEventId":670,"presenters":"Katy B&#246;rner###katy_borner.html"},
	{"presentationEventId":560,"presenters":"Angela Zoss###"},
	{"presentationEventId":117,"presenters":"Katy B&#246;rner###katy_borner.html"},
	{"presentationEventId":438,"presenters":"Katy B&#246;rner###katy_borner.html"},
	{"presentationEventId":709,"presenters":"Andreas Bueckle###andreas_bueckle.html"},
	{"presentationEventId":708,"presenters":"Katy B&#246;rner###katy_borner.html"},
	{"presentationEventId":697,"presenters":"Katy B&#246;rner###katy_borner.html"},
	{"presentationEventId":553,"presenters":"Katy B&#246;rner###katy_borner.html"},
	{"presentationEventId":309,"presenters":"Scott B. Weingart###http://www.scottbot.net/"},
	{"presentationEventId":349,"presenters":"Katy B&#246;rner###katy_borner.html"},
	{"presentationEventId":363,"presenters":"Katy B&#246;rner###katy_borner.html"},
	{"presentationEventId":341,"presenters":"Dr. Dowman P. Varn###"},
	{"presentationEventId":632,"presenters":"Katy B&#246;rner###katy_borner.html@@@Lisel Record###lisel_record.html@@@Bruce W. Herr II###bruce-herr.html@@@Randy Heiland###@@@James P. Sluka###@@@Leonard Cross###leonard_cross.html@@@Paul Macklin###"},
	{"presentationEventId":286,"presenters":"Katy B&#246;rner###katy_borner.html"},
	{"presentationEventId":409,"presenters":"Katy B&#246;rner###katy_borner.html"},
	{"presentationEventId":676,"presenters":"Katy B&#246;rner###katy_borner.html"},
	{"presentationEventId":155,"presenters":"Bruce W. Herr II###bruce-herr.html"},
	{"presentationEventId":446,"presenters":"Katy B&#246;rner###katy_borner.html"},
	{"presentationEventId":417,"presenters":"Katy B&#246;rner###katy_borner.html"},
	{"presentationEventId":434,"presenters":"Katy B&#246;rner###katy_borner.html@@@Robert Light###@@@Daniel Halsey###daniel_halsey.html"},
	{"presentationEventId":587,"presenters":"Katy B&#246;rner###katy_borner.html"},
	{"presentationEventId":605,"presenters":"Katy B&#246;rner###katy_borner.html@@@Paul Macklin###"},
	{"presentationEventId":710,"presenters":"Katy B&#246;rner###katy_borner.html"},
	{"presentationEventId":717,"presenters":"Leah Scherschel###leah_scherschel.html"},
	{"presentationEventId":691,"presenters":"Andreas Bueckle###andreas_bueckle.html"},
	{"presentationEventId":389,"presenters":"Katy B&#246;rner###katy_borner.html"},
	{"presentationEventId":97,"presenters":"Soma Sanyal###"},
	{"presentationEventId":702,"presenters":"Katy B&#246;rner###katy_borner.html"},
	{"presentationEventId":205,"presenters":"Katy B&#246;rner###katy_borner.html"},
	{"presentationEventId":197,"presenters":"Katy B&#246;rner###katy_borner.html"},
	{"presentationEventId":639,"presenters":"Katy B&#246;rner###katy_borner.html"},
	{"presentationEventId":447,"presenters":"Katy B&#246;rner###katy_borner.html"},
	{"presentationEventId":750,"presenters":"Katy B&#246;rner###katy_borner.html"},
	{"presentationEventId":114,"presenters":"Katy B&#246;rner###katy_borner.html"},
	{"presentationEventId":558,"presenters":"Katy B&#246;rner###katy_borner.html"},
	{"presentationEventId":351,"presenters":"Chin Hua Kong###@@@Katy B&#246;rner###katy_borner.html"},
	{"presentationEventId":302,"presenters":"Katy B&#246;rner###katy_borner.html"},
	{"presentationEventId":249,"presenters":"Mark Meiss###"},
	{"presentationEventId":269,"presenters":"Katy B&#246;rner###katy_borner.html"},
	{"presentationEventId":126,"presenters":"Katy B&#246;rner###katy_borner.html"},
	{"presentationEventId":194,"presenters":"Katy B&#246;rner###katy_borner.html"},
	{"presentationEventId":511,"presenters":"Katy B&#246;rner###katy_borner.html"},
	{"presentationEventId":534,"presenters":"Lisel Record###lisel_record.html"},
	{"presentationEventId":430,"presenters":"Katy B&#246;rner###katy_borner.html"},
	{"presentationEventId":316,"presenters":"Katy B&#246;rner###katy_borner.html"},
	{"presentationEventId":132,"presenters":"Katy B&#246;rner###katy_borner.html"},
	{"presentationEventId":520,"presenters":"Katy B&#246;rner###katy_borner.html"},
	{"presentationEventId":688,"presenters":"Katy B&#246;rner###katy_borner.html@@@Kristin Ardlie###"},
	{"presentationEventId":378,"presenters":"Katy B&#246;rner###katy_borner.html"},
	{"presentationEventId":369,"presenters":"Katy B&#246;rner###katy_borner.html"},
	{"presentationEventId":721,"presenters":"Katy B&#246;rner###katy_borner.html"},
	{"presentationEventId":742,"presenters":"Yashvardhan Jain###yashvardhan-jain.html"},
	{"presentationEventId":724,"presenters":"Zorina Galis###"},
	{"presentationEventId":67,"presenters":"Katy B&#246;rner###katy_borner.html"},
	{"presentationEventId":457,"presenters":"Katy B&#246;rner###katy_borner.html"},
	{"presentationEventId":464,"presenters":"Katy B&#246;rner###katy_borner.html"},
	{"presentationEventId":352,"presenters":"Katy B&#246;rner###katy_borner.html"},
	{"presentationEventId":395,"presenters":"David E. Polley###"},
	{"presentationEventId":703,"presenters":"Katy B&#246;rner###katy_borner.html@@@Michael Ginda###michael_ginda.html"},
	{"presentationEventId":567,"presenters":"Katy B&#246;rner###katy_borner.html@@@Lisel Record###lisel_record.html"},
	{"presentationEventId":224,"presenters":"Katy B&#246;rner###katy_borner.html"},
	{"presentationEventId":735,"presenters":"Katy B&#246;rner###katy_borner.html"},
	{"presentationEventId":660,"presenters":"Katy B&#246;rner###katy_borner.html"},
	{"presentationEventId":658,"presenters":"Katy B&#246;rner###katy_borner.html"},
	{"presentationEventId":513,"presenters":"Katy B&#246;rner###katy_borner.html"},
	{"presentationEventId":586,"presenters":"Katy B&#246;rner###katy_borner.html"},
	{"presentationEventId":51,"presenters":"Katy B&#246;rner###katy_borner.html"},
	{"presentationEventId":76,"presenters":"Peter A Hook###http://ella.slis.indiana.edu/~pahook/"},
	{"presentationEventId":406,"presenters":"Katy B&#246;rner###katy_borner.html"},
	{"presentationEventId":460,"presenters":"Katy B&#246;rner###katy_borner.html"},
	{"presentationEventId":69,"presenters":"Shashikant Penumarthy###"},
	{"presentationEventId":334,"presenters":"Katy B&#246;rner###katy_borner.html"},
	{"presentationEventId":203,"presenters":"Katy B&#246;rner###katy_borner.html"},
	{"presentationEventId":441,"presenters":"Katy B&#246;rner###katy_borner.html"},
	{"presentationEventId":393,"presenters":"David E. Polley###"},
	{"presentationEventId":591,"presenters":"Katy B&#246;rner###katy_borner.html"},
	{"presentationEventId":81,"presenters":"Peter A Hook###http://ella.slis.indiana.edu/~pahook/"},
	{"presentationEventId":219,"presenters":"Angela Zoss###"},
	{"presentationEventId":557,"presenters":"Katy B&#246;rner###katy_borner.html"},
	{"presentationEventId":273,"presenters":"Katy B&#246;rner###katy_borner.html"},
	{"presentationEventId":521,"presenters":"Katy B&#246;rner###katy_borner.html@@@Philip Beesley###"},
	{"presentationEventId":79,"presenters":"Katy B&#246;rner###katy_borner.html"},
	{"presentationEventId":42,"presenters":"Katy B&#246;rner###katy_borner.html"},
	{"presentationEventId":450,"presenters":"Katy B&#246;rner###katy_borner.html"},
	{"presentationEventId":715,"presenters":"Katy B&#246;rner###katy_borner.html"},
	{"presentationEventId":134,"presenters":"Peter A Hook###http://ella.slis.indiana.edu/~pahook/"},
	{"presentationEventId":59,"presenters":"Kevin W. Boyack###@@@Peter A Hook###http://ella.slis.indiana.edu/~pahook/"},
	{"presentationEventId":192,"presenters":"Katy B&#246;rner###katy_borner.html@@@Bruce W. Herr II###bruce-herr.html@@@Shashikant Penumarthy###"},
	{"presentationEventId":338,"presenters":"Katy B&#246;rner###katy_borner.html"},
	{"presentationEventId":271,"presenters":"Katy B&#246;rner###katy_borner.html"},
	{"presentationEventId":734,"presenters":"Andreas Bueckle###andreas_bueckle.html"},
	{"presentationEventId":116,"presenters":"Katy B&#246;rner###katy_borner.html"},
	{"presentationEventId":350,"presenters":"Katy B&#246;rner###katy_borner.html"},
	{"presentationEventId":607,"presenters":"Michael Ginda###michael_ginda.html@@@Katy B&#246;rner###katy_borner.html@@@Naren Suri###"},
	{"presentationEventId":235,"presenters":"Katy B&#246;rner###katy_borner.html"},
	{"presentationEventId":394,"presenters":"David E. Polley###"},
	{"presentationEventId":248,"presenters":"Katy B&#246;rner###katy_borner.html"},
	{"presentationEventId":387,"presenters":"Scott B. Weingart###http://www.scottbot.net/"},
	{"presentationEventId":84,"presenters":"Peter A Hook###http://ella.slis.indiana.edu/~pahook/"},
	{"presentationEventId":207,"presenters":"Russell Jackson Duhon###"},
	{"presentationEventId":74,"presenters":"Katy B&#246;rner###katy_borner.html"},
	{"presentationEventId":418,"presenters":"Katy B&#246;rner###katy_borner.html"},
	{"presentationEventId":6,"presenters":"Bruce W. Herr II###bruce-herr.html@@@Ben Markines###"},
	{"presentationEventId":509,"presenters":"Katy B&#246;rner###katy_borner.html"},
	{"presentationEventId":463,"presenters":"Katy B&#246;rner###katy_borner.html"},
	{"presentationEventId":246,"presenters":"Angela Zoss###@@@Michael Conover###@@@Katy B&#246;rner###katy_borner.html"},
	{"presentationEventId":29,"presenters":"Katy B&#246;rner###katy_borner.html"},
	{"presentationEventId":488,"presenters":"Daniel Halsey###daniel_halsey.html"},
	{"presentationEventId":41,"presenters":"Katy B&#246;rner###katy_borner.html"},
	{"presentationEventId":516,"presenters":"Katy B&#246;rner###katy_borner.html"},
	{"presentationEventId":713,"presenters":"Griffin Weber###"},
	{"presentationEventId":580,"presenters":"Olga Scrivner###olga-scrivner.html@@@Julie  Madewell###"},
	{"presentationEventId":698,"presenters":"Katy B&#246;rner###katy_borner.html"},
	{"presentationEventId":720,"presenters":"Katy B&#246;rner###katy_borner.html"},
	{"presentationEventId":564,"presenters":"Katy B&#246;rner###katy_borner.html@@@H. Eugene Stanley###@@@Paul Trunfio###@@@William Rouse###"},
	{"presentationEventId":539,"presenters":"Katy B&#246;rner###katy_borner.html"},
	{"presentationEventId":402,"presenters":"Katy B&#246;rner###katy_borner.html"},
	{"presentationEventId":467,"presenters":"Katy B&#246;rner###katy_borner.html@@@Robert Light###@@@Ashwin Nimhan###"},
	{"presentationEventId":648,"presenters":"Katy B&#246;rner###katy_borner.html"},
	{"presentationEventId":227,"presenters":"Katy B&#246;rner###katy_borner.html"},
	{"presentationEventId":247,"presenters":"Katy B&#246;rner###katy_borner.html"},
	{"presentationEventId":380,"presenters":"Katy B&#246;rner###katy_borner.html"},
	{"presentationEventId":311,"presenters":"Katy B&#246;rner###katy_borner.html"},
	{"presentationEventId":347,"presenters":"Katy B&#246;rner###katy_borner.html"},
	{"presentationEventId":410,"presenters":"Michael Ginda###michael_ginda.html"},
	{"presentationEventId":517,"presenters":"Katy B&#246;rner###katy_borner.html"},
	{"presentationEventId":138,"presenters":"Katy B&#246;rner###katy_borner.html"},
	{"presentationEventId":242,"presenters":"Katy B&#246;rner###katy_borner.html"},
	{"presentationEventId":190,"presenters":"Katy B&#246;rner###katy_borner.html"},
	{"presentationEventId":16,"presenters":"Stacy Kowalczyk###"},
	{"presentationEventId":680,"presenters":"Todd Theriault###todd_theriault.html"},
	{"presentationEventId":54,"presenters":"Ning Yu###"},
	{"presentationEventId":342,"presenters":"Dr. Dowman P. Varn###"},
	{"presentationEventId":574,"presenters":"Katy B&#246;rner###katy_borner.html"},
	{"presentationEventId":115,"presenters":"Katy B&#246;rner###katy_borner.html"},
	{"presentationEventId":148,"presenters":"Katy B&#246;rner###katy_borner.html"},
	{"presentationEventId":236,"presenters":"Katy B&#246;rner###katy_borner.html"},
	{"presentationEventId":208,"presenters":"Katy B&#246;rner###katy_borner.html"},
	{"presentationEventId":323,"presenters":"Katy B&#246;rner###katy_borner.html"},
	{"presentationEventId":678,"presenters":"Katy B&#246;rner###katy_borner.html"},
	{"presentationEventId":322,"presenters":"Katy B&#246;rner###katy_borner.html"},
	{"presentationEventId":294,"presenters":"Katy B&#246;rner###katy_borner.html"},
	{"presentationEventId":368,"presenters":"Robert Light###"},
	{"presentationEventId":36,"presenters":"Katy B&#246;rner###katy_borner.html"},
	{"presentationEventId":174,"presenters":"Katy B&#246;rner###katy_borner.html"},
	{"presentationEventId":451,"presenters":"Daniel Halsey###daniel_halsey.html"},
	{"presentationEventId":4,"presenters":"Ning Yu###"},
	{"presentationEventId":407,"presenters":"Katy B&#246;rner###katy_borner.html"},
	{"presentationEventId":200,"presenters":"Katy B&#246;rner###katy_borner.html"},
	{"presentationEventId":257,"presenters":"Katy B&#246;rner###katy_borner.html"},
	{"presentationEventId":53,"presenters":"Katy B&#246;rner###katy_borner.html"},
	{"presentationEventId":275,"presenters":"Katy B&#246;rner###katy_borner.html"},
	{"presentationEventId":613,"presenters":"Katy B&#246;rner###katy_borner.html@@@Mike Hu###"},
	{"presentationEventId":92,"presenters":"Bruce W. Herr II###bruce-herr.html"},
	{"presentationEventId":23,"presenters":"Katy B&#246;rner###katy_borner.html@@@Ketan K. Mane###@@@Emilia P. Martins###@@@Terry J. Ord###@@@Sidharth Thakur###"},
	{"presentationEventId":44,"presenters":"Katy B&#246;rner###katy_borner.html"},
	{"presentationEventId":583,"presenters":"Katy B&#246;rner###katy_borner.html"},
	{"presentationEventId":371,"presenters":"Katy B&#246;rner###katy_borner.html"},
	{"presentationEventId":650,"presenters":"Katy B&#246;rner###katy_borner.html"},
	{"presentationEventId":568,"presenters":"Katy B&#246;rner###katy_borner.html"},
	{"presentationEventId":726,"presenters":"Katy B&#246;rner###katy_borner.html"},
	{"presentationEventId":754,"presenters":"Andreas Bueckle###andreas_bueckle.html"},
	{"presentationEventId":677,"presenters":"Katy B&#246;rner###katy_borner.html"},
	{"presentationEventId":58,"presenters":"Katy B&#246;rner###katy_borner.html"},
	{"presentationEventId":1,"presenters":"Ketan K. Mane###"},
	{"presentationEventId":666,"presenters":"Katy B&#246;rner###katy_borner.html"},
	{"presentationEventId":290,"presenters":"Katy B&#246;rner###katy_borner.html"},
	{"presentationEventId":682,"presenters":"Katy B&#246;rner###katy_borner.html"},
	{"presentationEventId":111,"presenters":"Katy B&#246;rner###katy_borner.html"},
	{"presentationEventId":206,"presenters":"Russell Jackson Duhon###"},
	{"presentationEventId":562,"presenters":"Katy B&#246;rner###katy_borner.html"},
	{"presentationEventId":608,"presenters":"Michael Ginda###michael_ginda.html@@@Michael C. Richey###@@@Mark Cousino###@@@Katy B&#246;rner###katy_borner.html"},
	{"presentationEventId":237,"presenters":"Katy B&#246;rner###katy_borner.html"},
	{"presentationEventId":364,"presenters":"Katy B&#246;rner###katy_borner.html"},
	{"presentationEventId":372,"presenters":"David E. Polley###"},
	{"presentationEventId":86,"presenters":"Katy B&#246;rner###katy_borner.html"},
	{"presentationEventId":49,"presenters":"Katy B&#246;rner###katy_borner.html"},
	{"presentationEventId":572,"presenters":"Olga Scrivner###olga-scrivner.html"},
	{"presentationEventId":360,"presenters":"David E. Polley###@@@Katy B&#246;rner###katy_borner.html"},
	{"presentationEventId":70,"presenters":"Ketan K. Mane###"},
	{"presentationEventId":45,"presenters":"Katy B&#246;rner###katy_borner.html"},
	{"presentationEventId":743,"presenters":"Andreas Bueckle###andreas_bueckle.html@@@Lu Chen###"},
	{"presentationEventId":225,"presenters":"Katy B&#246;rner###katy_borner.html"},
	{"presentationEventId":199,"presenters":"Katy B&#246;rner###katy_borner.html"},
	{"presentationEventId":495,"presenters":"Katy B&#246;rner###katy_borner.html"},
	{"presentationEventId":611,"presenters":"Katy B&#246;rner###katy_borner.html@@@Bruce W. Herr II###bruce-herr.html"},
	{"presentationEventId":60,"presenters":"Katy B&#246;rner###katy_borner.html"},
	{"presentationEventId":671,"presenters":"Katy B&#246;rner###katy_borner.html@@@Yingnan Ju###"},
	{"presentationEventId":618,"presenters":"Anurag Joshi###@@@Olga Scrivner###olga-scrivner.html@@@Katy B&#246;rner###katy_borner.html@@@David Lebhar###@@@Kosali Simon###@@@Coady Wing###@@@Vatsal Jatakia###@@@Roshith Raghavan###@@@Livia Crim###"},
	{"presentationEventId":422,"presenters":"Katy B&#246;rner###katy_borner.html"},
	{"presentationEventId":105,"presenters":"A. Das###@@@Susan C. Herring###http://www.slis.indiana.edu/faculty/herring/@@@Shashikant Penumarthy###"},
	{"presentationEventId":327,"presenters":"Katy B&#246;rner###katy_borner.html"},
	{"presentationEventId":668,"presenters":"Lisel Record###lisel_record.html"},
	{"presentationEventId":75,"presenters":"Katy B&#246;rner###katy_borner.html@@@Bruce W. Herr II###bruce-herr.html"},
	{"presentationEventId":469,"presenters":"Katy B&#246;rner###katy_borner.html"},
	{"presentationEventId":124,"presenters":"Peter A Hook###http://ella.slis.indiana.edu/~pahook/"},
	{"presentationEventId":561,"presenters":"Katy B&#246;rner###katy_borner.html"},
	{"presentationEventId":245,"presenters":"Katy B&#246;rner###katy_borner.html@@@Angela Zoss###"},
	{"presentationEventId":415,"presenters":"Katy B&#246;rner###katy_borner.html"},
	{"presentationEventId":425,"presenters":"Katy B&#246;rner###katy_borner.html"},
	{"presentationEventId":43,"presenters":"Katy B&#246;rner###katy_borner.html"},
	{"presentationEventId":747,"presenters":"Katy B&#246;rner###katy_borner.html"},
	{"presentationEventId":220,"presenters":"Katy B&#246;rner###katy_borner.html"},
	{"presentationEventId":259,"presenters":"Katy B&#246;rner###katy_borner.html"},
	{"presentationEventId":166,"presenters":"Katy B&#246;rner###katy_borner.html"},
	{"presentationEventId":573,"presenters":"Katy B&#246;rner###katy_borner.html"},
	{"presentationEventId":731,"presenters":"Katy B&#246;rner###katy_borner.html"},
	{"presentationEventId":522,"presenters":" CNS###@@@ IUNI###@@@ UITS###"},
	{"presentationEventId":291,"presenters":"Katy B&#246;rner###katy_borner.html"},
	{"presentationEventId":423,"presenters":"CREST ###http://crest.iu.edu/"},
	{"presentationEventId":3,"presenters":"Katy B&#246;rner###katy_borner.html@@@Nikki A. Roberg###"},
	{"presentationEventId":431,"presenters":"Katy B&#246;rner###katy_borner.html@@@Andr&#233; Skupin###http://geography.sdsu.edu/People/Pages/skupin/index.htm@@@Julia Laurin###"},
	{"presentationEventId":645,"presenters":"Katy B&#246;rner###katy_borner.html"},
	{"presentationEventId":746,"presenters":"Andreas Bueckle###andreas_bueckle.html"},
	{"presentationEventId":201,"presenters":"Katy B&#246;rner###katy_borner.html"},
	{"presentationEventId":597,"presenters":"Katy B&#246;rner###katy_borner.html"},
	{"presentationEventId":61,"presenters":"Katy B&#246;rner###katy_borner.html@@@Andr&#233; Skupin###http://geography.sdsu.edu/People/Pages/skupin/index.htm"},
	{"presentationEventId":176,"presenters":"Katy B&#246;rner###katy_borner.html"},
	{"presentationEventId":87,"presenters":"Katy B&#246;rner###katy_borner.html@@@Weixia (Bonnie) Huang###@@@Bruce W. Herr II###bruce-herr.html"},
	{"presentationEventId":388,"presenters":"Katy B&#246;rner###katy_borner.html"},
	{"presentationEventId":14,"presenters":"Peter A Hook###http://ella.slis.indiana.edu/~pahook/"},
	{"presentationEventId":598,"presenters":"Lisel Record###lisel_record.html"},
	{"presentationEventId":344,"presenters":"David M. Coe###@@@Joseph R. Biberstine###"},
	{"presentationEventId":476,"presenters":"Andreas Bueckle###andreas_bueckle.html"},
	{"presentationEventId":121,"presenters":"Weixia (Bonnie) Huang###"},
	{"presentationEventId":634,"presenters":"Katy B&#246;rner###katy_borner.html"},
	{"presentationEventId":659,"presenters":"Katy B&#246;rner###katy_borner.html"},
	{"presentationEventId":210,"presenters":"Katy B&#246;rner###katy_borner.html"},
	{"presentationEventId":716,"presenters":"Leah Scherschel###leah_scherschel.html"},
	{"presentationEventId":161,"presenters":"Katy B&#246;rner###katy_borner.html@@@Maggie B. Swan###@@@Susan C. Herring###http://www.slis.indiana.edu/faculty/herring/"},
	{"presentationEventId":154,"presenters":"Russell Jackson Duhon###@@@Ann L McCranie###"},
	{"presentationEventId":584,"presenters":"Katy B&#246;rner###katy_borner.html"},
	{"presentationEventId":602,"presenters":"Lisel Record###lisel_record.html"},
	{"presentationEventId":657,"presenters":"Aaron M. Kipp###@@@Olga B. Scrivner###@@@Kimberly Goodyear###@@@Mikael Lehoux###"},
	{"presentationEventId":503,"presenters":"Katy B&#246;rner###katy_borner.html@@@Michael Ginda###michael_ginda.html"},
	{"presentationEventId":173,"presenters":"Timothy Kelley###"},
	{"presentationEventId":592,"presenters":"Katy B&#246;rner###katy_borner.html"},
	{"presentationEventId":753,"presenters":"Andreas Bueckle###andreas_bueckle.html"},
	{"presentationEventId":448,"presenters":"Katy B&#246;rner###katy_borner.html"},
	{"presentationEventId":491,"presenters":"Katy B&#246;rner###katy_borner.html"},
	{"presentationEventId":306,"presenters":"Katy B&#246;rner###katy_borner.html@@@Chintan Tank###@@@Chin Hua Kong###"},
	{"presentationEventId":757,"presenters":"Katy B&#246;rner###katy_borner.html"},
	{"presentationEventId":527,"presenters":"Katy B&#246;rner###katy_borner.html"},
	{"presentationEventId":345,"presenters":"Katy B&#246;rner###katy_borner.html"},
	{"presentationEventId":436,"presenters":"Katy B&#246;rner###katy_borner.html"},
	{"presentationEventId":150,"presenters":"Weixia (Bonnie) Huang###"},
	{"presentationEventId":308,"presenters":"Scott B. Weingart###http://www.scottbot.net/"},
	{"presentationEventId":420,"presenters":"Katy B&#246;rner###katy_borner.html"},
	{"presentationEventId":490,"presenters":"Katy B&#246;rner###katy_borner.html"},
	{"presentationEventId":331,"presenters":"Katy B&#246;rner###katy_borner.html"},
	{"presentationEventId":63,"presenters":"Stacy Kowalczyk###"},
	{"presentationEventId":9,"presenters":"Katy B&#246;rner###katy_borner.html"},
	{"presentationEventId":711,"presenters":"Andreas Bueckle###andreas_bueckle.html"},
	{"presentationEventId":260,"presenters":"Katy B&#246;rner###katy_borner.html"},
	{"presentationEventId":411,"presenters":"Katy B&#246;rner###katy_borner.html"},
	{"presentationEventId":445,"presenters":"Robert Light###"},
	{"presentationEventId":749,"presenters":"Katy B&#246;rner###katy_borner.html@@@Bruce W. Herr II###bruce-herr.html"},
	{"presentationEventId":118,"presenters":"Peter A Hook###http://ella.slis.indiana.edu/~pahook/"},
	{"presentationEventId":130,"presenters":"Katy B&#246;rner###katy_borner.html"},
	{"presentationEventId":272,"presenters":"Micah Linnemeier###@@@Chintan Tank###@@@Katy B&#246;rner###katy_borner.html"},
	{"presentationEventId":223,"presenters":"Katy B&#246;rner###katy_borner.html"},
	{"presentationEventId":240,"presenters":"Katy B&#246;rner###katy_borner.html@@@Yu-Chen (Alan) Lin###"},
	{"presentationEventId":283,"presenters":"Katy B&#246;rner###katy_borner.html"},
	{"presentationEventId":217,"presenters":"Katy B&#246;rner###katy_borner.html"},
	{"presentationEventId":231,"presenters":"Katy B&#246;rner###katy_borner.html"},
	{"presentationEventId":548,"presenters":"Andreas Bueckle###andreas_bueckle.html@@@Yingnan Ju###"},
	{"presentationEventId":538,"presenters":"Katy B&#246;rner###katy_borner.html"},
	{"presentationEventId":212,"presenters":"Katy B&#246;rner###katy_borner.html"},
	{"presentationEventId":383,"presenters":"Robert Light###@@@Chin Hua Kong###"},
	{"presentationEventId":328,"presenters":"Katy B&#246;rner###katy_borner.html"},
	{"presentationEventId":612,"presenters":"Katy B&#246;rner###katy_borner.html@@@Mike Hu###"},
	{"presentationEventId":263,"presenters":"Katy B&#246;rner###katy_borner.html"},
	{"presentationEventId":740,"presenters":"Bruce W. Herr II###bruce-herr.html"},
	{"presentationEventId":616,"presenters":"Katy B&#246;rner###katy_borner.html@@@Mike Hu###"},
	{"presentationEventId":615,"presenters":"Katy B&#246;rner###katy_borner.html@@@Mike Hu###"},
	{"presentationEventId":144,"presenters":"Katy B&#246;rner###katy_borner.html"},
	{"presentationEventId":7,"presenters":"Katy B&#246;rner###katy_borner.html"},
	{"presentationEventId":453,"presenters":"Katy B&#246;rner###katy_borner.html"}
]
